nprxchange/__init__.py
nprxchange/api.py
nprxchange/cli.py
nprxchange/converter.py
nprxchange/storage.py
nprxchange-0.1.1.dist-info/licenses/LICENSE
nprxchange-0.1.1.dist-info/METADATA
nprxchange-0.1.1.dist-info/WHEEL
nprxchange-0.1.1.dist-info/entry_points.txt
nprxchange-0.1.1.dist-info/top_level.txt
nprxchange-0.1.1.dist-info/RECORD
